mds_pycounts_yzeng/__init__.py
mds_pycounts_yzeng/mds_pycounts_yzeng.py
mds_pycounts_yzeng/plotting.py
mds_pycounts_yzeng-0.1.0.dist-info/LICENSE
mds_pycounts_yzeng-0.1.0.dist-info/METADATA
mds_pycounts_yzeng-0.1.0.dist-info/WHEEL
mds_pycounts_yzeng-0.1.0.dist-info/RECORD
